smsactivatepy/__init__.py
smsactivatepy/api.py
smsactivatepy-1.dist-info/METADATA
smsactivatepy-1.dist-info/WHEEL
smsactivatepy-1.dist-info/top_level.txt
smsactivatepy-1.dist-info/RECORD
