Metadata-Version: 2.1
Name: smsactivatepy
Version: 1
Summary: smsactivatepy is an Python module that provides functions for working with the API sms-activate.org
Author: Gabriel Lima
Author-email: gabrielmrts@yahoo.com
Classifier: Programming Language :: Python :: 3
Classifier: License :: OSI Approved :: MIT License
Classifier: Operating System :: OS Independent
Requires-Python: >=3.6
